xpystac/__init__.py
xpystac/_icechunk.py
xpystac/_xstac_kerchunk.py
xpystac/core.py
xpystac/py.typed
xpystac/utils.py
xpystac/xarray_plugin.py
xpystac-0.5.0.dist-info/licenses/LICENSE
xpystac-0.5.0.dist-info/METADATA
xpystac-0.5.0.dist-info/WHEEL
xpystac-0.5.0.dist-info/entry_points.txt
xpystac-0.5.0.dist-info/top_level.txt
xpystac-0.5.0.dist-info/RECORD
