Metadata-Version: 2.4
Name: xpystac
Version: 0.5.0
Summary: Extend xarray.open_dataset to accept pystac objects
Author-email: Julia Signell <jsignell@element84.com>
License: MIT
Project-URL: Home, https://github.com/stac-utils/xpystac
Project-URL: Repository, https://github.com/stac-utils/xpystac
Classifier: License :: OSI Approved :: MIT License
Requires-Python: >=3.11
License-File: LICENSE
Requires-Dist: xarray
Requires-Dist: pystac>=1.0.1
Dynamic: license-file
